ingestion/__init__.py
ingestion/apis.py
ingestion/exceptions.py
ingestion/ingestors.py
ingestion/logconfig.py
ingestion/main.py
ingestion/writers.py
av_tweet_ingestion-1.0.5.dist-info/METADATA
av_tweet_ingestion-1.0.5.dist-info/WHEEL
av_tweet_ingestion-1.0.5.dist-info/top_level.txt
av_tweet_ingestion-1.0.5.dist-info/RECORD
