Metadata-Version: 2.1
Name: av-tweet-ingestion
Version: 1.0.5
Summary: Ingests tweets using Twitter's RecentAPI.
Home-page: https://github.com/andreveit/av-tweet-ingestion
Author: Andre Veit
Author-email: andrev.veit@gmail.com
License: MIT
Classifier: License :: OSI Approved :: MIT License
Classifier: Programming Language :: Python :: 3
Classifier: Programming Language :: Python :: 3.10
Requires-Dist: requests
Requires-Dist: botocore
Requires-Dist: backoff
Requires-Dist: boto3
Requires-Dist: python-dotenv
Requires-Dist: ratelimit
